{
    "students": [
        {
            "username": "smith1234",
            "password": "password1",
            "firstname" : "John", 
            "lastname" : "Smith",
            "ID" : 9847584938,
            "phone" : "(555)-555-9859",
            "address" : "353 August Lane. Shreveport, LA. 71118",
            "birthday" : "9/14/1998",
            "lastLoginTime" : "2018-02-24 21:49:52",
            "lastLoginIP" : "170.122.222.14",
            "loginTimes" : "18 times",
            "onlineTime" : "15334 seconds", 
            "quiz1" : 10,
            "quiz2": 9,
            "midterm" : 49,
            "quiz3" : 8,
            "quiz4" : 10,
            "final" : 90
        },
        {
            "username": "johnson34",
            "password": "qwerty4",
            "firstname" : "Emily", 
            "lastname" : "Johnson",
            "phone" : "(555)-555-9987",
            "address" : "373 Lee Avenue. Camden, NJ. 08104",
            "birthday" : "6/14/1995",
            "lastLoginTime" : "2018-06-21 15:59:13",
            "lastLoginIP" : "64.89.104.180",
            "loginTimes" : "14 times",
            "onlineTime" : "3640 seconds",
            "ID" : 8758493837, 
            "quiz1" : 5,
            "quiz2": 7,
            "midterm" : 45,
            "quiz3" : 9,
            "quiz4" : 3,
            "final" : 92
        },
        {
            "username": "williams84",
            "password": "Wi11iam",
            "firstname" : "Oliver", 
            "lastname" : "Williams",
            "phone" : "(555)-555-8484",
            "address" : "1429 Lonely Oak Drive. Mobile, AL. 36602",
            "birthday" : "5/27/1998",
            "lastLoginTime" : "2018-03-04 10:36:11",
            "lastLoginIP" : "74.127.132.48",
            "loginTimes" : "19 times",
            "onlineTime" : "18321 seconds",
            "ID" : 7658475643, 
            "quiz1" : 8,
            "quiz2": 0,
            "midterm" : 36,
            "quiz3" : 3,
            "quiz4" : 4,
            "final" : 77
        },
        {
            "username": "jones189",
            "password": "121212",
            "firstname" : "Sophia", 
            "lastname" : "Jones",
            "phone" : "(555)-555-9932",
            "address" : "3579 Cedarstone Drive. Defiance, OH. 43512",
            "birthday" : "10/2/1994",
            "lastLoginTime" : "2018-02-15 14:05:01",
            "lastLoginIP" : "199.102.227.141",
            "loginTimes" : "20 times",
            "onlineTime" : "9200 seconds",
            "ID" : 4567483745, 
            "quiz1" : 9,
            "quiz2": 7,
            "midterm" : 48,
            "quiz3" : 9,
            "quiz4" : 4,
            "final" : 87
        },
        {
            "username": "brown76",
            "password": "54321",
            "firstname" : "Jack", 
            "lastname" : "Brown",
            "phone" : "(555)-555-1293",
            "address" : "4050 Poco Mas Drive. Dallas, TX. 75207",
            "birthday" : "11/14/1992",
            "lastLoginTime" : "2018-07-29 03:45:66",
            "lastLoginIP" : "128.41.8.17",
            "loginTimes" : "23 times",
            "onlineTime" : "15620 seconds",
            "ID" : 2347854345, 
            "quiz1" : 9,
            "quiz2": 8,
            "midterm" : 39,
            "quiz3" : 6,
            "quiz4" : 7,
            "final" : 87
        },
        {
            "username": "davis42",
            "password": "zigzag",
            "firstname" : "Isabelle", 
            "lastname" : "Davis",
            "phone" : "(555)-555-8843",
            "address" : "3905 Valley Lane. Austin, TX. 78749",
            "birthday" : "11/14/1992",
            "lastLoginTime" : "2018-06-23 07:47:26",
            "lastLoginIP" : "198.61.5.10",
            "loginTimes" : "5 times",
            "onlineTime" : "14630 seconds",
            "ID" : 87990933345, 
            "quiz1" : 2,
            "quiz2": 5,
            "midterm" : 28,
            "quiz3" : 3,
            "quiz4" : 8,
            "final" : 67
        },
        {
            "username": "miller66",
            "password": "987654321",
            "firstname" : "Noah", 
            "lastname" : "Miller",
            "phone" : "(555)-555-1293",
            "address" : "1830 Evergreen Lane. Rialto, CA. 92376",
            "birthday" : "7/15/1999",
            "lastLoginTime" : "2018-03-16 08:03:01",
            "lastLoginIP" : "165.22.188.148",
            "loginTimes" : "7 times",
            "onlineTime" : "455 seconds",
            "ID" : 8756675849, 
            "quiz1" : 7,
            "quiz2": 5,
            "midterm" : 45,
            "quiz3" : 9,
            "quiz4" : 10,
            "final" : 93
        },
        {
            "username": "wilson32",
            "password": "1q2w3e",
            "firstname" : "Isabelle", 
            "lastname" : "Wilson",
            "phone" : "(555)-555-9334",
            "address" : "3845 Morris Street. San Antonio, TX. 78205",
            "birthday" : "4/3/1994",
            "lastLoginTime" : "2018-02-03 23:55:47",
            "lastLoginIP" : "199.96.205.110",
            "loginTimes" : "16 times",
            "onlineTime" : "4608 seconds",
            "ID" : 8898743221, 
            "quiz1" : 8,
            "quiz2": 5,
            "midterm" : 43,
            "quiz3" : 3,
            "quiz4" : 7,
            "final" : 84
        },
        {
            "username": "James27",
            "password": "abc123",
            "firstname" : "Jacob", 
            "lastname" : "James",
            "phone" : "(555)-555-3455",
            "address" : "2389 Modoc Alley. Eagle, ID. 83642",
            "birthday" : "5/7/1994",
            "lastLoginTime" : "2018-10-28 01:30:33",
            "lastLoginIP" : "156.23.179.155",
            "loginTimes" : "17 times",
            "onlineTime" : "40309 seconds",
            "ID" : 3384749383, 
            "quiz1" : 9,
            "quiz2": 4,
            "midterm" : 43,
            "quiz3" : 8,
            "quiz4" : 3,
            "final" : 91
        },
        {
            "username": "moore9",
            "password": "123321",
            "firstname" : "Lily", 
            "lastname" : "Moore",
            "phone" : "(555)-555-5634",
            "address" : "4110 Saint Clair Street. Jackson, MS. 39213",
            "birthday" : "10/16/1998",
            "lastLoginTime" : "2015-11-13 17:25:46",
            "lastLoginIP" : "165.150.77.160",
            "loginTimes" : "12 times",
            "onlineTime" : "5080 seconds",
            "ID" : 3338459878, 
            "quiz1" : 6,
            "quiz2": 3,
            "midterm" : 25,
            "quiz3" : 0,
            "quiz4" : 2,
            "final" : 78
        }
    ]
 }